nvidia/cuda_sanitizer_api/bin/compute-sanitizer
nvidia/cuda_sanitizer_api/include/generated_cudaGL_meta.h
nvidia/cuda_sanitizer_api/include/generated_cudaVDPAU_meta.h
nvidia/cuda_sanitizer_api/include/generated_cuda_gl_interop_meta.h
nvidia/cuda_sanitizer_api/include/generated_cuda_meta.h
nvidia/cuda_sanitizer_api/include/generated_cuda_profiler_api_meta.h
nvidia/cuda_sanitizer_api/include/generated_cuda_runtime_api_meta.h
nvidia/cuda_sanitizer_api/include/generated_cuda_vdpau_interop_meta.h
nvidia/cuda_sanitizer_api/include/sanitizer.h
nvidia/cuda_sanitizer_api/include/sanitizer_barrier.h
nvidia/cuda_sanitizer_api/include/sanitizer_callbacks.h
nvidia/cuda_sanitizer_api/include/sanitizer_driver_cbid.h
nvidia/cuda_sanitizer_api/include/sanitizer_memory.h
nvidia/cuda_sanitizer_api/include/sanitizer_patching.h
nvidia/cuda_sanitizer_api/include/sanitizer_result.h
nvidia/cuda_sanitizer_api/include/sanitizer_runtime_cbid.h
nvidia/cuda_sanitizer_api/include/sanitizer_stream.h
nvidia/cuda_sanitizer_api/lib/libInterceptorInjectionTarget.so
nvidia/cuda_sanitizer_api/lib/libTreeLauncherPlaceholder.so
nvidia/cuda_sanitizer_api/lib/libTreeLauncherTargetInjection.so
nvidia/cuda_sanitizer_api/lib/libTreeLauncherTargetUpdatePreloadInjection.so
nvidia/cuda_sanitizer_api/lib/libsanitizer-collection.so
nvidia/cuda_sanitizer_api/lib/libsanitizer-public.so
nvidia_cuda_sanitizer_api_cu12-12.9.79.dist-info/licenses/License.txt
nvidia_cuda_sanitizer_api_cu12-12.9.79.dist-info/METADATA
nvidia_cuda_sanitizer_api_cu12-12.9.79.dist-info/WHEEL
nvidia_cuda_sanitizer_api_cu12-12.9.79.dist-info/top_level.txt
nvidia_cuda_sanitizer_api_cu12-12.9.79.dist-info/RECORD
